dtl_functions_rd/__init__.py
dtl_functions_rd/dtl_functions_rd.py
dtl_functions_rd/examples.py
dtl_functions_rd-0.1.4.dist-info/METADATA
dtl_functions_rd-0.1.4.dist-info/WHEEL
dtl_functions_rd-0.1.4.dist-info/RECORD
