Metadata-Version: 2.1
Name: dtl_functions_rd
Version: 0.1.4
Summary: A sample library of Data Transformation functions.
License: MIT
Author: repeckadonatas
Author-email: repeckadonatas@yahoo.com
Requires-Python: >=3.11,<4.0
Classifier: License :: OSI Approved :: MIT License
Classifier: Programming Language :: Python :: 3
Classifier: Programming Language :: Python :: 3.11
Classifier: Programming Language :: Python :: 3.12
Requires-Dist: mypy (>=1.8.0,<2.0.0)
Requires-Dist: numpy (>=1.26.3,<2.0.0)
